harpo/__init__.py
harpo/cli/__init__.py
harpo/cli/domain/__init__.py
harpo/cli/domain/commands.py
harpo/cli/group/__init__.py
harpo/cli/group/commands.py
harpo/cli/key/__init__.py
harpo/cli/key/commands.py
harpo/cli/secret/__init__.py
harpo/cli/secret/commands.py
harpo/cli/system/__init__.py
harpo/cli/system/commands.py
harpo/cli/user/__init__.py
harpo/cli/user/commands.py
harpo/cli/util.py
harpo/domain/__init__.py
harpo/domain/domain.py
harpo/domain/manager.py
harpo/exceptions.py
harpo/exporter.py
harpo/group/__init__.py
harpo/group/group.py
harpo/group/manager.py
harpo/key/__init__.py
harpo/key/manager.py
harpo/log.py
harpo/main.py
harpo/meta.py
harpo/secret.py
harpo/user/__init__.py
harpo/user/manager.py
harpo/user/user.py
harpo/util.py
harpo-1.4.2.dist-info/LICENSE
harpo-1.4.2.dist-info/METADATA
harpo-1.4.2.dist-info/WHEEL
harpo-1.4.2.dist-info/entry_points.txt
harpo-1.4.2.dist-info/RECORD
