Metadata-Version: 2.1
Name: harpo
Version: 1.4.2
Summary: A GPG-based secret storing/sharing library
License: Apache-2.0
Author: Behavox DevOps
Author-email: devops@behavox.com
Requires-Python: >=3.7,<4.0.0
Classifier: Development Status :: 4 - Beta
Classifier: Environment :: Console
Classifier: Intended Audience :: Developers
Classifier: Intended Audience :: Information Technology
Classifier: Intended Audience :: System Administrators
Classifier: License :: OSI Approved :: Apache Software License
Classifier: Operating System :: MacOS :: MacOS X
Classifier: Operating System :: POSIX :: Linux
Classifier: Programming Language :: Python
Classifier: Programming Language :: Python :: 3
Classifier: Programming Language :: Python :: 3.7
Classifier: Programming Language :: Python :: 3.8
Classifier: Programming Language :: Python :: 3.9
Classifier: Programming Language :: Python :: 3.10
Classifier: Programming Language :: Python :: 3.11
Classifier: Topic :: Security :: Cryptography
Provides-Extra: buildtools
Provides-Extra: publish
Requires-Dist: PyYAML (>=6.0.0,<7.0.0)
Requires-Dist: click (>=8.1.7,<9.0.0)
Requires-Dist: colorlog (>=6.7.0,<7.0.0)
Requires-Dist: filelock (>=3.0.12)
Requires-Dist: pbr (>=5.11.1,<6.0.0)
Requires-Dist: python-gnupg (==0.5.1)
Requires-Dist: setuptools[buildtools] (>=62.2.0) ; extra == "buildtools"
Requires-Dist: six (>=1.16.0,<2.0.0)
Requires-Dist: tabulate (>=0.9.0,<0.10.0)
Requires-Dist: twine[publish] (>=4.0.2,<5.0.0) ; extra == "publish"
Requires-Dist: wheel[buildtools] (>=0.41.3,<0.42.0) ; extra == "buildtools"
